MANIFEST.in
requirements.txt
setup.py
tox.ini
odata2avro/__init__.py
odata2avro/main.py
odata2avro.egg-info/PKG-INFO
odata2avro.egg-info/SOURCES.txt
odata2avro.egg-info/dependency_links.txt
odata2avro.egg-info/entry_points.txt
odata2avro.egg-info/requires.txt
odata2avro.egg-info/top_level.txt