Metadata-Version: 1.1
Name: odata2avro
Version: 1.0.0
Summary: Convert OData datasets to Avro
Home-page: https://github.com/datadudes/odata2avro
Author: Marcel Krcah, Daan Debie
Author-email: marcel.krcah@gmail.com, debie.daan@gmail.com
License: MIT
Keywords: azure odata avro impala hive hadoop
Platform: UNKNOWN
Classifier: Development Status :: 5 - Production/Stable
Classifier: Environment :: Console
Classifier: Intended Audience :: Developers
Classifier: License :: OSI Approved :: MIT License
Classifier: Operating System :: POSIX
Classifier: Operating System :: MacOS
Classifier: Operating System :: Unix
Classifier: Programming Language :: Python
Classifier: Programming Language :: Python :: 2
Classifier: Topic :: Database
Classifier: Topic :: Utilities
